Workbook

Sheet Cover
A1: Visa Inc. (NYSE: V) — Professional DCF Valuation Upgrade
A3: Prepared | B3: 2026-07-08
A4: Recommendation | B4: Neutral / Hold
A5: Base Case Implied Share Price | B5: =DCF!B24
A6: Current Share Price | B6: =Assumptions!B4
A7: Model standard | B7: IB analyst model with driver-based revenue build, scenarios, football field, bridge, sensitivity, sources appendix
A10: VP Review Comments
A11: • Forecast upgraded from top-down growth to category-level driver build (service, data processing, international, other, less incentives).
A12: • WACC inputs now include explicit public source notes and separate cost of debt proxy.
A13: • Added Bear/Base/Bull DCF, football field, valuation bridge, color-formatted sensitivity table, charts and source appendix.

Sheet Exec Summary
A1: Executive Summary — VP Review Output
A3: Recommendation | B3: Neutral / Hold
A4: Base Case Implied Share Price | B4: =DCF!B24
A5: Current Share Price | B5: =DCF!B25
A6: Upside / (Downside) | B6: =DCF!B26
A7: WACC | B7: =WACC!B18
A8: Terminal Growth | B8: =Assumptions!B20
A11: Model Upgrades Completed
A12: • Driver-based revenue build by Visa reporting category: service, data processing, international, other, less client incentives.
A13: • Explicit WACC source notes: FRED DGS10, 5-year weekly beta vs SPY, ERP assumption, FRED AAA corporate yield proxy.
A14: • Bull / Base / Bear scenario outputs with different revenue growth, margin, WACC and terminal growth assumptions.
A15: • Football field valuation, enterprise-to-equity valuation bridge, sensitivity heat map, charts and sources appendix.
A16: • Investment recommendation reframed with buy/hold/upgrade/downgrade triggers.
A19: Scenario Summary
A20: Metric | B20: Bear | C20: Base | D20: Bull
A21: Implied Share Price | B21: ='Scenarios'!B9 | C21: ='Scenarios'!C9 | D21: ='Scenarios'!D9
A22: Upside / (Downside) | B22: ='Scenarios'!B10 | C22: ='Scenarios'!C10 | D22: ='Scenarios'!D10
A23: Revenue CAGR FY25-FY30 | B23: ='Scenarios'!B5 | C23: ='Scenarios'!C5 | D23: ='Scenarios'!D5
A24: FY30E Operating Margin | B24: ='Scenarios'!B6 | C24: ='Scenarios'!C6 | D24: ='Scenarios'!D6
A25: Terminal Growth | B25: ='Scenarios'!B8 | C25: ='Scenarios'!C8 | D25: ='Scenarios'!D8
A29: VP Recommendation
A30: Visa is an exceptional franchise, but the base-case intrinsic value remains below the latest trading price. Maintain Neutral / Hold unless the investor can underwrite the Bull case or buy closer to the base-case valuation range.

Sheet Historical
A1: Historical Financial Analysis
A3: Fiscal year ending Sep. 30 | B3: FY20A | C3: FY21A | D3: FY22A | E3: FY23A | F3: FY24A | G3: FY25A
A5: Revenue | B5: 21846 | C5: 24105 | D5: 29310 | E5: 32653 | F5: 35926 | G5: 40000
A6: Revenue Growth | C6: =C5/B5-1 | D6: =D5/C5-1 | E6: =E5/D5-1 | F6: =F5/E5-1 | G6: =G5/F5-1
A7: Operating Income | B7: 14081 | C7: 15804 | D7: 18813 | E7: 21000 | F7: 23595 | G7: 23994
A8: Operating Margin | B8: =B7/B5 | C8: =C7/C5 | D8: =D7/D5 | E8: =E7/E5 | F8: =F7/F5 | G8: =G7/G5
A9: Net Income | B9: 10866 | C9: 12311 | D9: 14957 | E9: 17273 | F9: 19743 | G9: 20058
A10: Net Margin | B10: =B9/B5 | C10: =C9/C5 | D10: =D9/D5 | E10: =E9/E5 | F10: =F9/F5 | G10: =G9/G5
A11: D&A | B11: 767 | C11: 804 | D11: 861 | E11: 943 | F11: 1034 | G11: 1220
A12: Capex | B12: 736 | C12: 705 | D12: 970 | E12: 1059 | F12: 1257 | G12: 1482
A13: Cash Flow from Operations | B13: 10440 | C13: 15227 | D13: 18849 | E13: 20755 | F13: 19950 | G13: 23059
A14: FCF (CFO - Capex) | B14: =B13-B12 | C14: =C13-C12 | D14: =D13-D12 | E14: =E13-E12 | F14: =F13-F12 | G14: =G13-G12
A15: FCF Margin | B15: =B14/B5 | C15: =C14/C5 | D15: =D14/D5 | E15: =E14/E5 | F15: =F14/F5 | G15: =G14/G5
A16: Pre-tax Income | B16: 13790 | C16: 16063 | D16: 18136 | E16: 21037 | F16: 23916 | G16: 24194
A17: Tax Expense | B17: 2924 | C17: 3752 | D17: 3179 | E17: 3764 | F17: 4173 | G17: 4136

Sheet Revenue Build
A1: Driver-Based Revenue Build
A3: Fiscal year | B3: FY20A | C3: FY21A | D3: FY22A | E3: FY23A | F3: FY24A | G3: FY25A | H3: FY26E | I3: FY27E | J3: FY28E | K3: FY29E | L3: FY30E
A5: Service Revenue | B5: 9804 | C5: 11475 | D5: 13361 | E5: 14826 | F5: 16114 | G5: 17539 | H5: 19205.205 | I5: 20837.647 | J5: 22400.471 | K5: 23856.502 | L5: 25287.892
A6: Data Processing Revenue | B6: 10975 | C6: 12792 | D6: 14438 | E6: 16007 | F6: 17714 | G6: 19993 | H6: 22292.195 | I6: 24521.414 | J6: 26728.342 | K6: 28866.609 | L6: 30887.272
A7: International Transaction Revenue | B7: 6299 | C7: 6530 | D7: 9815 | E7: 11638 | F7: 12665 | G7: 14166 | H7: 15936.75 | I7: 17689.792 | J7: 19370.323 | K7: 20919.949 | L7: 22384.345
A8: Other Revenue | B8: 1432 | C8: 1675 | D8: 1991 | E8: 2479 | F8: 3197 | G8: 4053 | H8: 4782.54 | I8: 5499.921 | J8: 6159.9115 | K8: 6775.9027 | L8: 7317.9749
A9: Gross Revenue | B9: =SUM(B5:B8) | C9: =SUM(C5:C8) | D9: =SUM(D5:D8) | E9: =SUM(E5:E8) | F9: =SUM(F5:F8) | G9: =SUM(G5:G8) | H9: =SUM(H5:H8) | I9: =SUM(I5:I8) | ... L9: =SUM(L5:L8)
A10: Client Incentives | B10: 6664 | C10: 8367 | D10: 10295 | E10: 12297 | F10: 13764 | G10: 15751 | H10: 17641.12 | I10: 19493.438 | J10: 21247.847 | K10: 22947.675 | L10: 24554.012
A11: Net Revenue | B11: 21846 | C11: 24105 | D11: 29310 | E11: 32653 | F11: 35926 | G11: 40000 | H11: =H9-H10 | I11: =I9-I10 | J11: =J9-J10 | K11: =K9-K10 | L11: =L9-L10
A12: Net Revenue Growth | C12: =C11/B11-1 | D12: =D11/C11-1 | E12: =E11/D11-1 | F12: =F11/E11-1 | G12: =G11/F11-1 | H12: =H11/G11-1 | I12: =I11/H11-1 | J12: =J11/I11-1 | ... L12: =L11/K11-1
A15: Base Case Category Growth Assumptions | B15: FY26E | C15: FY27E | D15: FY28E | E15: FY29E | F15: FY30E
A16: Service Revenue | B16: 0.095 | C16: 0.085 | D16: 0.075 | E16: 0.065 | F16: 0.06
A17: Data Processing Revenue | B17: 0.115 | C17: 0.1 | D17: 0.09 | E17: 0.08 | F17: 0.07
A18: International Transaction Revenue | B18: 0.125 | C18: 0.11 | D18: 0.095 | E18: 0.08 | F18: 0.07
A19: Other Revenue | B19: 0.18 | C19: 0.15 | D19: 0.12 | E19: 0.1 | F19: 0.08
A20: Client Incentives | B20: 0.12 | C20: 0.105 | D20: 0.09 | E20: 0.08 | F20: 0.07

Sheet Assumptions
A1: Assumptions & Source Notes
A3: Market / Capital Structure | B3: Value | C3: Source / Rationale
A4: Current Share Price | B4: 352.2 | C4: Yahoo Finance chart API regular market price, 2026-07-07
A5: Diluted / As-Converted Shares | B5: 1894 | C5: Visa latest 10-Q as-converted share disclosure (2026-03-31, filed 2026-04-29)
A6: Cash & Cash Equivalents | B6: 12404 | C6: Visa latest balance sheet, 2026-03-31
A7: Current Investments | B7: 1509 | C7: Visa latest balance sheet, 2026-03-31
A8: Long-term Investments | B8: 308 | C8: Visa latest balance sheet, 2026-03-31
A9: Total Debt | B9: 23976 | C9: Visa latest balance sheet, 2026-03-31
A10: Cash + Investments | B10: =SUM(B6:B8) | C10: Cash plus current and long-term investments
A11: Net Debt | B11: =B9-B10 | C11: Debt less cash + investments
A14: WACC Inputs | B14: Value | C14: Source / Rationale
A15: Risk-free Rate | B15: 0.0448 | C15: FRED DGS10, 2026-07-06
A16: Beta | B16: 0.84 | C16: 5-year weekly regression of V vs SPY, 261 observations from Yahoo chart API
A17: Equity Risk Premium | B17: 0.05 | C17: Analyst assumption; benchmarked to common U.S. ERP range / Damodaran-style market convention
A18: Pre-tax Cost of Debt | B18: 0.0507 | C18: FRED ICE BofA AAA corporate effective yield (BAMLC0A1CAAAEY), 2026-07-06
A19: Tax Rate | B19: 0.19 | C19: Normalized cash tax rate, cross-checked vs recent Visa effective tax rates
A20: Terminal Growth | B20: 0.035 | C20: Long-run nominal growth: approx. inflation plus real GDP; below explicit forecast CAGR and below WACC

Sheet Scenarios
A1: Bull / Base / Bear Scenario Analysis
A3: Scenario | B3: Bear | C3: Base | D3: Bull
A5: Revenue CAGR FY25-FY30 | B5: 0.047585814 | C5: 0.089214334 | D5: 0.11503787
A6: FY30E Operating Margin | B6: 0.625 | C6: 0.65 | D6: 0.66
A7: WACC | B7: 0.090213276 | C7: 0.085213276 | D7: 0.080213276
A8: Terminal Growth | B8: 0.025 | C8: 0.035 | D8: 0.04
A9: Implied Share Price | B9: 179.88081 | C9: 284.53977 | D9: 398.90858
A10: Upside / (Downside) | B10: -0.48926517 | C10: -0.19210741 | D10: 0.13261948
A13: VP Interpretation
A14: Bear case captures payment-volume deceleration / regulatory pressure; Bull case requires sustained high-teens VAS and international recovery plus margin expansion. Base case remains below current price, making valuation discipline the gating issue.

Sheet Forecast
A1: Base Case Operating Forecast
A3: Fiscal year | B3: FY26E | C3: FY27E | D3: FY28E | E3: FY29E | F3: FY30E
A5: Net Revenue | B5: ='Revenue Build'!H11 | C5: ='Revenue Build'!I11 | D5: ='Revenue Build'!J11 | E5: ='Revenue Build'!K11 | F5: ='Revenue Build'!L11
A6: Revenue Growth | B6: =B5/Historical!G5-1 | C6: =C5/B5-1 | D6: =D5/C5-1 | E6: =E5/D5-1 | F6: =F5/E5-1
A7: Operating Margin | B7: 0.63 | C7: 0.64 | D7: 0.645 | E7: 0.65 | F7: 0.65
A8: Operating Income | B8: =B5*B7 | C8: =C5*C7 | D8: =D5*D7 | E8: =E5*E7 | F8: =F5*F7
A9: Tax Rate | B9: =Assumptions!B19 | C9: =Assumptions!B19 | D9: =Assumptions!B19 | E9: =Assumptions!B19 | F9: =Assumptions!B19
A10: Tax Expense | B10: =B8*B9 | C10: =C8*C9 | D10: =D8*D9 | E10: =E8*E9 | F10: =F8*F9
A11: NOPAT | B11: =B8-B10 | C11: =C8-C10 | D11: =D8-D10 | E11: =E8-E10 | F11: =F8-F10
A12: D&A | B12: =B5*3.1% | C12: =C5*3.1% | D12: =D5*3.1% | E12: =E5*3.1% | F12: =F5*3.1%
A13: Capex | B13: =B5*3.6% | C13: =C5*3.6% | D13: =D5*3.6% | E13: =E5*3.6% | F13: =F5*3.6%
A14: Change in NWC | B14: =(B5-Historical!G5)*0.5% | C14: =(C5-B5)*0.5% | D14: =(D5-C5)*0.5% | E14: =(E5-D5)*0.5% | F14: =(F5-E5)*0.5%
A15: Unlevered FCF | B15: =B11+B12-B13-B14 | C15: =C11+C12-C13-C14 | D15: =D11+D12-D13-D14 | E15: =E11+E12-E13-E14 | F15: =F11+F12-F13-F14
A16: FCF Margin | B16: =B15/B5 | C16: =C15/C5 | D16: =D15/D5 | E16: =E15/E5 | F16: =F15/F5
A17: EBITDA | B17: =B8+B12 | C17: =C8+C12 | D17: =D8+D12 | E17: =E8+E12 | F17: =F8+F12

Sheet WACC
A1: WACC Calculation
A3: Item | B3: Value | C3: Source / Formula
A5: Share Price | B5: =Assumptions!B4 | C5: Yahoo chart API
A6: Shares | B6: =Assumptions!B5 | C6: Latest 10-Q as-converted
A7: Market Value of Equity | B7: =B5*B6 | C7: Price x shares
A8: Debt | B8: =Assumptions!B9 | C8: Latest balance sheet
A9: Risk-free Rate | B9: =Assumptions!B15 | C9: FRED DGS10
A10: Beta | B10: =Assumptions!B16 | C10: 5y weekly V vs SPY
A11: ERP | B11: =Assumptions!B17 | C11: Analyst assumption
A12: Cost of Equity | B12: =B9+B10*B11 | C12: CAPM
A13: Pre-tax Cost of Debt | B13: =Assumptions!B18 | C13: FRED AAA corporate yield
A14: Tax Rate | B14: =Assumptions!B19 | C14: Normalized
A15: After-tax Cost of Debt | B15: =B13*(1-B14) | C15: Kd x (1-tax)
A16: Equity Weight | B16: =B7/(B7+B8) | C16: Market-value weight
A17: Debt Weight | B17: =B8/(B7+B8) | C17: Market-value weight
A18: WACC | B18: =B12*B16+B15*B17 | C18: Weighted average

Sheet DCF
A1: Base Case DCF Valuation
A3: Fiscal year | B3: FY26E | C3: FY27E | D3: FY28E | E3: FY29E | F3: FY30E
A5: Unlevered FCF | B5: =Forecast!B15 | C5: =Forecast!C15 | D5: =Forecast!D15 | E5: =Forecast!E15 | F5: =Forecast!F15
A6: Discount Period | B6: 0.5 | C6: 1.5 | D6: 2.5 | E6: 3.5 | F6: 4.5
A7: Discount Factor | B7: =1/(1+$B$12)^B6 | C7: =1/(1+$B$12)^C6 | D7: =1/(1+$B$12)^D6 | E7: =1/(1+$B$12)^E6 | F7: =1/(1+$B$12)^F6
A8: PV of FCF | B8: =B5*B7 | C8: =C5*C7 | D8: =D5*D7 | E8: =E5*E7 | F8: =F5*F7
A12: WACC | B12: =WACC!B18
A13: Terminal Growth | B13: =Assumptions!B20
A15: PV Explicit FCFs | B15: =SUM(B8:F8)
A16: Terminal FCF | B16: =F5
A17: Terminal Value | B17: =B16*(1+B13)/(B12-B13)
A18: PV Terminal Value | B18: =B17/(1+B12)^5
A19: Enterprise Value | B19: =B15+B18
A20: Cash + Investments | B20: =Assumptions!B10
A21: Debt | B21: =Assumptions!B9
A22: Equity Value | B22: =B19+B20-B21
A23: Shares | B23: =Assumptions!B5
A24: Implied Share Price | B24: =B22/B23
A25: Current Share Price | B25: =Assumptions!B4
A26: Upside / (Downside) | B26: =B24/B25-1
A27: Terminal Value % EV | B27: =B18/B19

Sheet Football Field
A1: Football Field Valuation
A3: Method | B3: Low | C3: High | D3: Midpoint
A5: DCF Sensitivity | B5: 241.0794 | C5: 352.76458 | D5: =AVERAGE(B5:C5)
A6: Scenario DCF | B6: 179.88081 | C6: 398.90858 | D6: =AVERAGE(B6:C6)
A7: FY26E EV/EBITDA (19.0x–25.0x) | B7: 290.42745 | C7: 383.76784 | D7: =AVERAGE(B7:C7)
A8: FY26E P/E (23.0x–31.0x) | B8: 276.22968 | C8: 372.30956 | D8: =AVERAGE(B8:C8)
A9: 52-week trading range | B9: 293.89 | C9: 365.02 | D9: =AVERAGE(B9:C9)
A12: Current Share Price | B12: =Assumptions!B4

Sheet Valuation Bridge
A1: Valuation Bridge
A3: Bridge Item | B3: Value | C3: Comment
A5: Enterprise Value | B5: =DCF!B19 | C5: DCF-derived enterprise value
A6: Add: Cash + Investments | B6: =DCF!B20 | C6: Non-operating cash and investment securities
A7: Less: Debt | B7: =-DCF!B21 | C7: Debt deducted to equity value
A8: Equity Value | B8: =SUM(B5:B7) | C8: Implied market capitalization
A9: Shares Outstanding | B9: =DCF!B23 | C9: Diluted / as-converted shares
A10: Implied Share Price | B10: =B8/B9 | C10: Equity value per share
A11: Current Share Price | B11: =DCF!B25 | C11: Latest market price
A12: Value Gap | B12: =B10-B11 | C12: DCF less current price

Sheet Sensitivity
A1: Sensitivity Analysis — Implied Share Price
A3: WACC \ Terminal Growth | B3: 0.025 | C3: 0.03 | D3: 0.035 | E3: 0.04 | F3: 0.045
A5: 0.075 | B5: 295.82426 | C5: 323.904 | D5: 359.00367 | E5: 404.13182 | F5: 464.30269
A6: 0.08 | B6: 268.19523 | C6: 290.74706 | D6: 318.3104 | E6: 352.76458 | F6: 397.06281
A7: 0.085 | B7: 245.19447 | C7: 263.64363 | D7: 285.78262 | E7: 312.84138 | F7: 346.66484
A8: 0.09 | B8: 225.75305 | C8: 241.0794 | D8: 259.19236 | E8: 280.92792 | F8: 307.4936
A9: 0.095 | B9: 209.10746 | C9: 222.00603 | D9: 237.05436 | E9: 254.83875 | F9: 276.18002

Sheet Charts
A1: Charts
A3: Chart 1: Net Revenue & Unlevered FCF
B5: 2020 | C5: 2021 | D5: 2022 | E5: 2023 | F5: 2024 | G5: 2025 | H5: 2026 | I5: 2027 | J5: 2028 | K5: 2029 | L5: 2030
A6: Net Revenue | B6: 21846 | C6: 24105 | D6: 29310 | E6: 32653 | F6: 35926 | G6: 40000 | H6: 44575.57 | I6: 49055.338 | J6: 53411.2 | K6: 57471.287 | L6: 61323.471
A7: FCF | B7: 9704 | C7: 14522 | D7: 17879 | E7: 19696 | F7: 18693 | G7: 21577 | H7: 22501.158 | I7: 25162.612 | J7: 27615.846 | K7: 29950.976 | L7: 31960.929
A25: Scenario | B25: Implied Share Price
A26: Bear | B26: 179.88081
A27: Base | B27: 284.53977
A28: Bull | B28: 398.90858

Sheet Sources
A1: Appendix — Sources & Audit Trail
A3: Source | B3: Use | C3: Details
A4: Visa FY2025 Form 10-K | B4: Historical financials; revenue category data; business description | C4: Filed 2025-11-06 for period 2025-09-30
A5: Visa latest Form 10-Q | B5: Share count; latest balance sheet context | C5: Filed 2026-04-29 for period 2026-03-31
A6: SEC Company Facts API | B6: Historical statements and balance sheet line items | C6: CIK 0001403161
A7: Yahoo Finance chart API | B7: Current share price, 52-week range, beta price series | C7: Price date 2026-07-07
A8: FRED DGS10 | B8: Risk-free rate | C8: 4.48% as of 2026-07-06
A9: FRED ICE BofA AAA Corporate Yield | B9: Pre-tax cost of debt proxy | C9: 5.07% as of 2026-07-06
A10: Analyst assumptions | B10: ERP, forecast category growth, margins, terminal growth | C10: Documented on Assumptions / Revenue Build / Scenarios tabs

Sheet Risks
A1: Key Investment Risks & Diligence Questions
A3: Risk | B3: Why It Matters | C3: Diligence / Monitoring
A4: Regulatory / interchange | B4: Network fees, routing and interchange caps can pressure yields or incentive intensity. | C4: Track DOJ / EU / local card network actions and settlement outcomes.
A5: Client incentives | B5: Competitive renewals can consume gross revenue growth. | C5: Monitor incentives as % gross revenue and renewal commentary.
A6: Macro / cross-border | B6: Travel and consumer spend are cyclical and FX-sensitive. | C6: Track cross-border ex intra-Europe and travel corridors.
A7: Competition | B7: A2A, wallets, RTP, domestic schemes and merchant steering can pressure growth. | C7: Track acceptance, tokenization and account-to-account adoption.
A8: Cyber / operational resilience | B8: Network outage or security events could damage trust. | C8: Review operational resilience disclosures and incident history.
A9: Valuation sensitivity | B9: Long-duration cash flows are rate and terminal-growth sensitive. | C9: Use WACC/g sensitivity and scenario matrix as valuation guardrails.
